src/__init__.py
src/cli.py
src/config.py
src/exceptions.py
src/logger.py
src/cryptography/__init__.py
src/cryptography/decrypt.py
src/cryptography/derivation.py
src/cryptography/encrypt.py
src/cryptography/password_handler.py
src/steganography/__init__.py
src/steganography/compressor.py
src/steganography/decoder.py
src/steganography/encoder.py
src/steganography/file_handler.py
stega_crypt-1.2.dist-info/licenses/LICENSE
stega_crypt-1.2.dist-info/METADATA
stega_crypt-1.2.dist-info/WHEEL
stega_crypt-1.2.dist-info/entry_points.txt
stega_crypt-1.2.dist-info/top_level.txt
stega_crypt-1.2.dist-info/RECORD
