Metadata-Version: 2.4
Name: stega-crypt
Version: 1.2
Summary: A steganography library with cryptography for hiding messages in images.
Home-page: https://github.com/Luca-02/stega-crypt
Author: Luca Milanesi
Author-email: milanesiluca2002@gmail.com
License: Apache License 2.0
Project-URL: Source Code, https://github.com/Luca-02/stega-crypt
Requires-Python: >=3.10
License-File: LICENSE
Requires-Dist: art==6.4
Requires-Dist: click==8.1.8
Requires-Dist: cryptography==44.0.2
Requires-Dist: numpy==2.2.4
Requires-Dist: Pillow==11.1.0
Requires-Dist: pycryptodome==3.22.0
Requires-Dist: setuptools==78.1.1
Dynamic: author
Dynamic: author-email
Dynamic: description
Dynamic: description-content-type
Dynamic: home-page
Dynamic: license
Dynamic: license-file
Dynamic: project-url
Dynamic: requires-dist
Dynamic: requires-python
Dynamic: summary
